vlcrc/__init__.py
vlcrc/__main__.py
vlcrc/vlc_remote_control.py
vlcrc-1.1.0.dist-info/LICENSE
vlcrc-1.1.0.dist-info/METADATA
vlcrc-1.1.0.dist-info/WHEEL
vlcrc-1.1.0.dist-info/entry_points.txt
vlcrc-1.1.0.dist-info/top_level.txt
vlcrc-1.1.0.dist-info/RECORD
