Metadata-Version: 2.1
Name: vlcrc
Version: 1.1.0
Summary: A Python library for remote control of VLC media player via its RC interface.
Author-email: Dolgii Evgenii <e.v.dolgii@gmail.com>
License: MIT License
Project-URL: Homepage, https://github.com/evgenii-d/vlcrc
Project-URL: Issues, https://github.com/evgenii-d/vlcrc/issues
Keywords: vlc,vlc media player,media player,remote control,remote,rc,VLC RC,VLC player remote,cli
Classifier: Development Status :: 5 - Production/Stable
Classifier: Intended Audience :: Developers
Classifier: Intended Audience :: End Users/Desktop
Classifier: Programming Language :: Python :: 3
Classifier: License :: OSI Approved :: MIT License
Classifier: Operating System :: OS Independent
Requires-Python: >=3.10
License-File: LICENSE
